megatts3/__init__.py
megatts3/cli.py
megatts3/download.py
megatts3/frontend_function.py
megatts3/gradio_api.py
megatts3/infer_cli.py
megatts3/modules/aligner/whisper_small.py
megatts3/modules/ar_dur/ar_dur_predictor.py
megatts3/modules/ar_dur/commons/layers.py
megatts3/modules/ar_dur/commons/nar_tts_modules.py
megatts3/modules/ar_dur/commons/rel_transformer.py
megatts3/modules/ar_dur/commons/rot_transformer.py
megatts3/modules/ar_dur/commons/seq_utils.py
megatts3/modules/ar_dur/commons/transformer.py
megatts3/modules/llm_dit/cfm.py
megatts3/modules/llm_dit/dit.py
megatts3/modules/llm_dit/time_embedding.py
megatts3/modules/llm_dit/transformer.py
megatts3/modules/wavvae/decoder/diag_gaussian.py
megatts3/modules/wavvae/decoder/hifigan_modules.py
megatts3/modules/wavvae/decoder/seanet_encoder.py
megatts3/modules/wavvae/decoder/wavvae_v3.py
megatts3/modules/wavvae/encoder/common_modules/conv.py
megatts3/modules/wavvae/encoder/common_modules/lstm.py
megatts3/modules/wavvae/encoder/common_modules/seanet.py
megatts3/utils/audio_utils/align.py
megatts3/utils/audio_utils/io.py
megatts3/utils/audio_utils/plot.py
megatts3/utils/commons/ckpt_utils.py
megatts3/utils/commons/hparams.py
megatts3/utils/text_utils/dict.json
megatts3/utils/text_utils/ph_tone_convert.py
megatts3/utils/text_utils/split_text.py
megatts3/utils/text_utils/text_encoder.py
tts_webui_megatts3-0.1.1.dist-info/licenses/LICENSE
tts_webui_megatts3-0.1.1.dist-info/METADATA
tts_webui_megatts3-0.1.1.dist-info/WHEEL
tts_webui_megatts3-0.1.1.dist-info/entry_points.txt
tts_webui_megatts3-0.1.1.dist-info/top_level.txt
tts_webui_megatts3-0.1.1.dist-info/RECORD
