Metadata-Version: 2.4
Name: tts-webui.megatts3
Version: 0.1.1
Summary: MegaTTS 3 - Zero-shot speech synthesis components as a Python library
Author: ByteDance (upstream) / community packaging
License: 
Keywords: tts,speech-synthesis,diffusion,whisper,pytorch
Classifier: Programming Language :: Python :: 3
Classifier: Programming Language :: Python :: 3.10
Classifier: Programming Language :: Python :: 3.11
Classifier: License :: OSI Approved :: Apache Software License
Classifier: Operating System :: OS Independent
Requires-Python: <4,>=3.10
License-File: LICENSE
Requires-Dist: torch<3,>=2.1
Requires-Dist: numpy<2,>=1.23
Requires-Dist: librosa>=0.10
Requires-Dist: transformers<5,>=4.41
Requires-Dist: einops>=0.6
Requires-Dist: scipy>=1.10
Requires-Dist: pydub<1,>=0.25
Requires-Dist: pyloudnorm<1,>=0.1
Requires-Dist: WeTextProcessing<2,>=1.0.4
Requires-Dist: langdetect>=1.0.9
Requires-Dist: six>=1.16
Requires-Dist: PyYAML>=6.0
Requires-Dist: tqdm>=4.66
Requires-Dist: huggingface_hub<1,>=0.24
Provides-Extra: ui
Requires-Dist: gradio<6,>=5; extra == "ui"
Provides-Extra: align
Requires-Dist: openai-whisper==20240930; extra == "align"
Provides-Extra: plot
Requires-Dist: matplotlib>=3.7; extra == "plot"
Dynamic: license-file
